README.md
pyproject.toml
src/cpp/ikfast.h
src/cpp/left_arm_ik.cpp
src/cpp/right_arm_ik.cpp
src/pr2_ikfast/__init__.py
src/pr2_ikfast.egg-info/PKG-INFO
src/pr2_ikfast.egg-info/SOURCES.txt
src/pr2_ikfast.egg-info/dependency_links.txt
src/pr2_ikfast.egg-info/requires.txt
src/pr2_ikfast.egg-info/top_level.txt