Metadata-Version: 2.1
Name: pr2_ikfast
Version: 0.0.3
Summary: Python bindings for the PR2 IKFast library
Requires-Python: >=3.8
Requires-Dist: numpy
